hardware/elevator_controller.v
module elevator_controller (
    input clk,
    input reset,
    input request_valid,
    input [1:0] request_floor,
    output reg [1:0] current_floor,
    output reg moving,
    output reg direction
);

    // direction: 1 = up, 0 = down

    always @(posedge clk or posedge reset) begin
        if (reset) begin
            current_floor <= 2'd0;
            moving <= 1'b0;
            direction <= 1'b0;
        end else begin
            if (request_valid) begin
                if (current_floor < request_floor) begin
                    direction <= 1'b1;
                    moving <= 1'b1;
                    current_floor <= current_floor + 1'b1;
                end else if (current_floor > request_floor) begin
                    direction <= 1'b0;
                    moving <= 1'b1;
                    current_floor <= current_floor - 1'b1;
                end else begin
                    moving <= 1'b0;
                end
            end else begin
                moving <= 1'b0;
            end
        end
    end

endmodule

elevator_tb.v
module elevator_tb;

    reg clk;
    reg reset;
    reg request_valid;
    reg [1:0] request_floor;

    wire [1:0] current_floor;
    wire moving;
    wire direction;

    elevator_controller dut (
        .clk(clk),
        .reset(reset),
        .request_valid(request_valid),
        .request_floor(request_floor),
        .current_floor(current_floor),
        .moving(moving),
        .direction(direction)
    );

    always #5 clk = ~clk;

    initial begin
        $dumpfile("wave.vcd");
        $dumpvars(0, elevator_tb);

        clk = 0;
        reset = 1;
        request_valid = 0;
        request_floor = 0;

        #10 reset = 0;

        #10 request_floor = 2'd3;
            request_valid = 1;

        #40 request_valid = 0;

        #20 request_floor = 2'd1;
            request_valid = 1;

        #40 request_valid = 0;

        #50 $finish;
    end

endmodule

wave.vcd
$date
	Wed Dec 17 21:15:12 2025
$end
$version
	Icarus Verilog
$end
$timescale
	1s
$end
$scope module elevator_tb $end
$var wire 1 ! moving $end
$var wire 1 " direction $end
$var wire 2 # current_floor [1:0] $end
$var reg 1 $ clk $end
$var reg 2 % request_floor [1:0] $end
$var reg 1 & request_valid $end
$var reg 1 ' reset $end
$scope module dut $end
$var wire 1 $ clk $end
$var wire 2 ( request_floor [1:0] $end
$var wire 1 & request_valid $end
$var wire 1 ' reset $end
$var reg 2 ) current_floor [1:0] $end
$var reg 1 " direction $end
$var reg 1 ! moving $end
$upscope $end
$upscope $end
$enddefinitions $end
$comment Show the parameter values. $end
$dumpall
$end
#0
$dumpvars
b0 )
b0 (
1'
0&
b0 %
0$
b0 #
0"
0!
$end
#5
1$
#10
0$
0'
#15
1$
#20
0$
1&
b11 %
b11 (
#25
b1 #
b1 )
1!
1"
1$
#30
0$
#35
b10 #
b10 )
1$
#40
0$
#45
b11 #
b11 )
1$
#50
0$
#55
0!
1$
#60
0$
0&
#65
1$
#70
0$
#75
1$
#80
0$
1&
b1 %
b1 (
#85
b10 #
b10 )
1!
0"
1$
#90
0$
#95
b1 #
b1 )
1$
#100
0$
#105
0!
1$
#110
0$
#115
1$
#120
0$
0&
